{"name":"Linked Data Wizards","tagline":"Explore and analyze Linked Data with the Linked Data Query Wizard and the Linked Data Visualization Wizard","body":"## Set up a local (development) instance\r\n\r\nYou can quickly set up a virtual machine containing a local instance of the Linked Data Wizards on Windows, Mac OS X, or Linux by following these simple instructions:\r\n\r\n* Make sure that you have [Vagrant](https://www.vagrantup.com/) and [VirtualBox](https://www.virtualbox.org/) installed.\r\n\r\n* Run the following commands:\r\n  ```\r\n  git clone https://github.com/patrickhoefler/linked-data-wizards\r\n  cd linked-data-wizards/dev\r\n  vagrant up\r\n  ```\r\n\r\nAfter a few minutes — depending on the speed of your Internet connection — your local instance should  be ready at http://192.168.33.10:8000/.\r\n\r\nAll changes to the source code should be immediately visible after you reload the respective page in the browser.\r\n\r\nYou can stop the virtual machine at any time by running `vagrant halt` and bring it back up again with `vagrant up`.\r\n\r\nFinally you can remove the virtual machine by running `vagrant destroy`.\r\n\r\n## Credits\r\n\r\nThe Linked Data Wizards were initially developed at the [Know-Center](http://know-center.at/) in Graz, Austria as part of the EU-funded [CODE project](http://code-research.eu/).","google":"","note":"Don't delete this file! It's used internally to help with page regeneration."}